{"event":[
{"active":false,"descr":"Случайный эффект каждые 30 минут с 9.00-19.00","crontab":"0 */30 9-19 * * *","cmd":"33=0"},
{"active":false,"descr":"приглушать звук МП3 в 23:00 ежедневно","crontab":"0 0 23 * * *","cmd":"40=5"},
{"active":false,"descr":"говорящие часы днем по будням каждые пол часа","crontab":"0 */30 * * * 1-5","cmd":"50=1"},
{"active":false,"descr":"ночной режим по будням","crontab":"35 23 W * *","cmd":"20=4,30=64"},
{"active":false,"descr":"по выходным вкл в 9 утра 13й эффект на 15й яркости","crontab":"0 0 9 * * SUN,SAT","cmd":"10=1,30=13,20=15"},
{"active":false,"descr":"случайные часы каждые 15 мин днём","crontab":"0 */15 9-19 * * *","cmd":"251=-1"}]
}